botpress_nlu_testing/.env
botpress_nlu_testing/__init__.py
botpress_nlu_testing/api.py
botpress_nlu_testing/bot_utils.py
botpress_nlu_testing/cli.py
botpress_nlu_testing/gui.py
botpress_nlu_testing/test_runner.py
botpress_nlu_testing/typings.py
botpress_nlu_testing-0.1.1.dist-info/entry_points.txt
botpress_nlu_testing-0.1.1.dist-info/LICENSE
botpress_nlu_testing-0.1.1.dist-info/WHEEL
botpress_nlu_testing-0.1.1.dist-info/METADATA
botpress_nlu_testing-0.1.1.dist-info/RECORD
