Metadata-Version: 2.1
Name: botpress-nlu-testing
Version: 0.1.1
Summary: A package to test botpress bots and return performance informations.
Author: Pierre Snell
Author-email: pierre.snell@botpress.com
Requires-Python: >=3.8,<4.0
Classifier: Programming Language :: Python :: 3
Classifier: Programming Language :: Python :: 3.8
Classifier: Programming Language :: Python :: 3.9
Classifier: Programming Language :: Python :: 3.10
Requires-Dist: click (>=8.0.3,<9.0.0)
Requires-Dist: dynaconf (>=3.1.7,<4.0.0)
Requires-Dist: numpy (>=1.22.1,<2.0.0)
Requires-Dist: pandas (>=1.4.0,<2.0.0)
Requires-Dist: requests (>=2.27.1,<3.0.0)
Requires-Dist: rich (>=11.1.0,<12.0.0)
Requires-Dist: scikit-learn (>=1.0.2,<2.0.0)
Requires-Dist: streamlit (>=1.5.0,<2.0.0)
